topsis.py
topsis_package/__init__.py
topsis_package/topsis.py
mytopsispackage-0.1.dist-info/METADATA
mytopsispackage-0.1.dist-info/WHEEL
mytopsispackage-0.1.dist-info/top_level.txt
mytopsispackage-0.1.dist-info/RECORD
